binancechain/__init__.py
binancechain/crypto.py
binancechain/enums.py
binancechain/exceptions.py
binancechain/httpclient.py
binancechain/noderpc.py
binancechain/ratelimit.py
binancechain/transaction.py
binancechain/transaction_base.py
binancechain/transaction_pb2.py
binancechain/wallet.py
binancechain/websocket.py
binancechain-0.1.6.dist-info/AUTHORS
binancechain-0.1.6.dist-info/LICENSE.txt
binancechain-0.1.6.dist-info/METADATA
binancechain-0.1.6.dist-info/WHEEL
binancechain-0.1.6.dist-info/top_level.txt
binancechain-0.1.6.dist-info/RECORD
